{
  "canSkip": false,
  "eventType": "EVENT",
  "choices": [
    {
      "index": 0,
      "nextEventId": 90100301
    },
    {
      "index": 1,
      "nextEventId": 90100302
    }
  ],
  "selectionEvents": {
    "1": {
      "canSkip": false,
      "eventType": "COIN_EVENT",
      "participantInfo": {
        "min": 1,
        "max": 1
      },
      "judgement": {
        "successThreshold": 8,
        "bestThreshold": 16,
        "affinities": [
          "CRIMSON",
          "SCARLET"
        ]
      },
      "results": [
        {
          "outcome": "SUCCESS",
          "effects": [
            {
              "effect": "GetConfirmedEgogift",
              "reward": {
                "type": "EGO_GIFT",
                "id": 9003,
                "num": 1,
                "prob": 1.0
              }
            }
          ]
        },
        {
          "outcome": "FAILURE",
          "effects": [
            {
              "effect": "Nothing"
            }
          ]
        }
      ]
    },
    "2": {
      "canSkip": false,
      "eventType": "COIN_EVENT",
      "participantInfo": {
        "min": 1,
        "max": 1
      },
      "judgement": {
        "successThreshold": 7,
        "bestThreshold": 14,
        "affinities": [
          "CRIMSON",
          "VIOLET"
        ]
      },
      "results": [
        {
          "outcome": "SUCCESS",
          "effects": [
            {
              "effect": "RecoverMpOnly_15",
              "target": "EveryAlly"
            }
          ]
        },
        {
          "outcome": "FAILURE",
          "effects": [
            {
              "effect": "LoseMpOnly_10",
              "target": "EveryAlly"
            }
          ]
        }
      ]
    }
  }
}