{
  "canSkip": false,
  "eventType": "EVENT",
  "choices": [
    {
      "index": 0,
      "nextEventId": 90101801
    },
    {
      "index": 1,
      "directEffects": [
        {
          "effect": "LoseHpOnly_10",
          "target": "RandomAlly_1",
          "condition": "NotIncludeSkillAttribute_CRIMSON",
          "descId": "Choice_901018"
        }
      ]
    },
    {
      "index": 2,
      "directEffects": [
        {
          "effect": "StartBattle_Abnormality",
          "nextBattleId": 2060026
        },
        {
          "effect": "GetConfirmedEgogiftOnWinBattle",
          "descId": "Choice_EGO901018",
          "reward": {
            "type": "EGO_GIFT",
            "id": 9018,
            "num": 1,
            "prob": 1
          }
        },
        {
          "effect": "GetConfirmedEgogiftOnWinBattle",
          "descId": "Choice_LoseBattle",
          "reward": {
            "type": "EGO_GIFT",
            "id": 9109,
            "num": 1,
            "prob": 1
          }
        }
      ]
    }
  ],
  "selectionEvents": {
    "1": {
      "canSkip": false,
      "eventType": "COIN_EVENT",
      "participantInfo": {
        "min": 1,
        "max": 1
      },
      "judgement": {
        "successThreshold": 9,
        "bestThreshold": 18,
        "affinities": [
          "SHAMROCK",
          "VIOLET"
        ]
      },
      "results": [
        {
          "outcome": "SUCCESS",
          "effects": [
            {
              "effect": "GetConfirmedEgogift",
              "reward": {
                "type": "EGO_GIFT",
                "id": 9018,
                "num": 1,
                "prob": 1.0
              }
            }
          ]
        },
        {
          "outcome": "FAILURE",
          "effects": [
            {
              "effect": "LoseMpOnly_12",
              "target": "ChosenPersonality",
              "condition": "FAILURE",
              "descId": "Choice_90101801"
            }
          ]
        }
      ]
    }
  }
}